AUTHORS.rst
HISTORY.rst
MANIFEST.in
README.rst
setup.cfg
setup.py
bin/__init__.py
bin/vagabond
bin/deathstar/Vagabond.py
vagabond/.vagabond.swp
vagabond/__init__.py
vagabond/vm.py
vagabond.egg-info/PKG-INFO
vagabond.egg-info/SOURCES.txt
vagabond.egg-info/dependency_links.txt
vagabond.egg-info/requires.txt
vagabond.egg-info/top_level.txt
vagabond/templates/Vagabond.py
vagabond/templates/__init__.py